mitmproxy_mcp/__init__.py
mitmproxy_mcp/__main__.py
mitmproxy_mcp/flow_utils.py
mitmproxy_mcp/json_utils.py
mitmproxy_mcp/protection_analysis.py
mitmproxy_mcp/server.py
iflow_mcp_mitmproxy_mcp-0.1.0.dist-info/METADATA
iflow_mcp_mitmproxy_mcp-0.1.0.dist-info/WHEEL
iflow_mcp_mitmproxy_mcp-0.1.0.dist-info/entry_points.txt
iflow_mcp_mitmproxy_mcp-0.1.0.dist-info/RECORD
