Metadata-Version: 2.4
Name: iflow-mcp_mitmproxy-mcp
Version: 0.1.0
Summary: A MCP server project
Author-email: Lucas Soeth <lucasoeth@gmail.com>
Requires-Python: >=3.11
Requires-Dist: mcp>=1.3.0
Requires-Dist: mitmproxy>=11.0.2
